cs/ffmpegutils.py
cs_ffmpegutils-20241122.dist-info/METADATA
cs_ffmpegutils-20241122.dist-info/WHEEL
cs_ffmpegutils-20241122.dist-info/entry_points.txt
cs_ffmpegutils-20241122.dist-info/top_level.txt
cs_ffmpegutils-20241122.dist-info/RECORD
