Metadata-Version: 2.1
Name: cs-ffmpegutils
Version: 20241122
Summary: Convenience facilities for using FFmpeg (ffmpeg.org), with invocation via `ffmpeg-python`.
Author-email: Cameron Simpson <cs@cskk.id.au>
License: GNU General Public License v3 or later (GPLv3+)
Project-URL: Monorepo Hg/Mercurial Mirror, https://hg.sr.ht/~cameron-simpson/css
Project-URL: Monorepo Git Mirror, https://github.com/cameron-simpson/css
Project-URL: MonoRepo Commits, https://bitbucket.org/cameron_simpson/css/commits/branch/main
Project-URL: Source, https://github.com/cameron-simpson/css/blob/main/lib/python/cs/ffmpegutils.py
Keywords: python3
Classifier: Programming Language :: Python
Classifier: Programming Language :: Python :: 3
Classifier: Development Status :: 4 - Beta
Classifier: Intended Audience :: Developers
Classifier: Operating System :: OS Independent
Classifier: Topic :: Software Development :: Libraries :: Python Modules
Classifier: License :: OSI Approved :: GNU General Public License v3 or later (GPLv3+)
Requires-Dist: cs.dockerutils>=20240519
Requires-Dist: cs.fstags>=20241122
Requires-Dist: cs.lex>=20241122
Requires-Dist: cs.logutils>=20241109
Requires-Dist: cs.mappings>=20231129
Requires-Dist: cs.pfx>=20240630
Requires-Dist: cs.psutils>=20241122
Requires-Dist: cs.tagset>=20241007
Requires-Dist: ffmpeg-python
Requires-Dist: typeguard
